MANIFEST.in
README.md
pyproject.toml
setup.py
message/__init__.py
message/apps.py
message/models.py
message/migrations/0001_initial.py
message/migrations/__init__.py
message/static/.DS_Store
message/static/jquery/jquery.min.js
message/static/sweetalert2/sweetalert2.all.js
message/static/sweetalert2/sweetalert2.all.min.js
message/static/sweetalert2/sweetalert2.css
message/static/sweetalert2/sweetalert2.js
message/static/sweetalert2/sweetalert2.min.css
message/static/sweetalert2/sweetalert2.min.js
message/static/toastr/toastr.css
message/static/toastr/toastr.js.map
message/static/toastr/toastr.min.css
message/static/toastr/toastr.min.js
message/templates/riso-message/messaging.html
message/templatetags/__init__.py
message/templatetags/swal_message.py
riso_message.egg-info/PKG-INFO
riso_message.egg-info/SOURCES.txt
riso_message.egg-info/dependency_links.txt
riso_message.egg-info/requires.txt
riso_message.egg-info/top_level.txt