Metadata-Version: 2.1
Name: riso-message
Version: 0.1.4
Summary: Django Message
Home-page: https://github.com/RisoTech-Hub/one-message
Author: Bin Nguyen
Author-email: tu.nguyen@risotech.vn
Classifier: Development Status :: 4 - Beta
Classifier: Framework :: Django
Classifier: Framework :: Django :: 4.2
Classifier: Intended Audience :: Developers
Classifier: Operating System :: OS Independent
Classifier: Programming Language :: Python
Classifier: Programming Language :: Python :: 3 :: Only
Classifier: Programming Language :: Python :: 3.11
Classifier: Topic :: Software Development :: Libraries :: Application Frameworks
Classifier: Topic :: Software Development :: Libraries :: Python Modules
Requires-Python: >=3.11
